i_got/__init__.py
i_got/__main__.py
i_got/common.py
i_got/extractor.py
i_got/json_output.py
i_got/version.py
i_got/cli_wrapper/__init__.py
i_got/cli_wrapper/downloader/__init__.py
i_got/cli_wrapper/openssl/__init__.py
i_got/cli_wrapper/player/__init__.py
i_got/cli_wrapper/player/__main__.py
i_got/cli_wrapper/player/dragonplayer.py
i_got/cli_wrapper/player/gnome_mplayer.py
i_got/cli_wrapper/player/mplayer.py
i_got/cli_wrapper/player/vlc.py
i_got/cli_wrapper/player/wmp.py
i_got/cli_wrapper/transcoder/__init__.py
i_got/cli_wrapper/transcoder/ffmpeg.py
i_got/cli_wrapper/transcoder/libav.py
i_got/cli_wrapper/transcoder/mencoder.py
i_got/extractors/__init__.py
i_got/extractors/acfun.py
i_got/extractors/alive.py
i_got/extractors/archive.py
i_got/extractors/baidu.py
i_got/extractors/bandcamp.py
i_got/extractors/baomihua.py
i_got/extractors/bigthink.py
i_got/extractors/bilibili.py
i_got/extractors/bokecc.py
i_got/extractors/cbs.py
i_got/extractors/ckplayer.py
i_got/extractors/cntv.py
i_got/extractors/coub.py
i_got/extractors/dailymotion.py
i_got/extractors/douban.py
i_got/extractors/douyin.py
i_got/extractors/douyutv.py
i_got/extractors/ehow.py
i_got/extractors/embed.py
i_got/extractors/facebook.py
i_got/extractors/fc2video.py
i_got/extractors/flickr.py
i_got/extractors/freesound.py
i_got/extractors/funshion.py
i_got/extractors/giphy.py
i_got/extractors/google.py
i_got/extractors/heavymusic.py
i_got/extractors/huomaotv.py
i_got/extractors/icourses.py
i_got/extractors/ifeng.py
i_got/extractors/imgur.py
i_got/extractors/infoq.py
i_got/extractors/instagram.py
i_got/extractors/interest.py
i_got/extractors/iqilu.py
i_got/extractors/iqiyi.py
i_got/extractors/iwara.py
i_got/extractors/ixigua.py
i_got/extractors/joy.py
i_got/extractors/kakao.py
i_got/extractors/khan.py
i_got/extractors/ku6.py
i_got/extractors/kuaishou.py
i_got/extractors/kugou.py
i_got/extractors/kuwo.py
i_got/extractors/le.py
i_got/extractors/lizhi.py
i_got/extractors/longzhu.py
i_got/extractors/lrts.py
igot-0.1.1.dist-info/LICENSE
igot-0.1.1.dist-info/METADATA
igot-0.1.1.dist-info/WHEEL
igot-0.1.1.dist-info/entry_points.txt
igot-0.1.1.dist-info/top_level.txt
igot-0.1.1.dist-info/zip-safe
igot-0.1.1.dist-info/RECORD
